odoo/addons/stock_picking_group_by_partner_by_carrier/README.rst
odoo/addons/stock_picking_group_by_partner_by_carrier/__init__.py
odoo/addons/stock_picking_group_by_partner_by_carrier/__manifest__.py
odoo/addons/stock_picking_group_by_partner_by_carrier/i18n/de.po
odoo/addons/stock_picking_group_by_partner_by_carrier/i18n/fr.po
odoo/addons/stock_picking_group_by_partner_by_carrier/i18n/it.po
odoo/addons/stock_picking_group_by_partner_by_carrier/i18n/stock_picking_group_by_partner_by_carrier.pot
odoo/addons/stock_picking_group_by_partner_by_carrier/models/__init__.py
odoo/addons/stock_picking_group_by_partner_by_carrier/models/procurement_group.py
odoo/addons/stock_picking_group_by_partner_by_carrier/models/res_partner.py
odoo/addons/stock_picking_group_by_partner_by_carrier/models/sale_order.py
odoo/addons/stock_picking_group_by_partner_by_carrier/models/stock_move.py
odoo/addons/stock_picking_group_by_partner_by_carrier/models/stock_picking.py
odoo/addons/stock_picking_group_by_partner_by_carrier/models/stock_picking_type.py
odoo/addons/stock_picking_group_by_partner_by_carrier/models/stock_rule.py
odoo/addons/stock_picking_group_by_partner_by_carrier/models/stock_warehouse.py
odoo/addons/stock_picking_group_by_partner_by_carrier/readme/CONTRIBUTORS.rst
odoo/addons/stock_picking_group_by_partner_by_carrier/readme/CREDITS.rst
odoo/addons/stock_picking_group_by_partner_by_carrier/readme/DESCRIPTION.rst
odoo/addons/stock_picking_group_by_partner_by_carrier/readme/USAGE.rst
odoo/addons/stock_picking_group_by_partner_by_carrier/report/__init__.py
odoo/addons/stock_picking_group_by_partner_by_carrier/report/assets.xml
odoo/addons/stock_picking_group_by_partner_by_carrier/report/report_delivery_slip.py
odoo/addons/stock_picking_group_by_partner_by_carrier/report/report_delivery_slip.xml
odoo/addons/stock_picking_group_by_partner_by_carrier/security/ir.model.access.csv
odoo/addons/stock_picking_group_by_partner_by_carrier/static/description/icon.png
odoo14_addon_stock_picking_group_by_partner_by_carrier-14.0.1.4.4.dist-info/METADATA
odoo14_addon_stock_picking_group_by_partner_by_carrier-14.0.1.4.4.dist-info/WHEEL
odoo14_addon_stock_picking_group_by_partner_by_carrier-14.0.1.4.4.dist-info/top_level.txt
odoo14_addon_stock_picking_group_by_partner_by_carrier-14.0.1.4.4.dist-info/RECORD
