Metadata-Version: 2.1
Name: odoo14-addon-stock-picking-group-by-partner-by-carrier
Version: 14.0.1.4.4
Summary: Stock Picking: group by partner and carrier
Home-page: https://github.com/OCA/stock-logistics-workflow
Author: Camptocamp, BCIM, Odoo Community Association (OCA)
Author-email: support@odoo-community.org
License: AGPL-3
Platform: UNKNOWN
Classifier: Programming Language :: Python
Classifier: Framework :: Odoo
Classifier: Framework :: Odoo :: 14.0
Classifier: License :: OSI Approved :: GNU Affero General Public License v3
Classifier: Development Status :: 5 - Production/Stable
Requires-Python: >=3.6
Requires-Dist: odoo14-addon-delivery-procurement-group-carrier
Requires-Dist: odoo14-addon-stock-move-assign-picking-hook
Requires-Dist: odoo <14.1dev,>=14.0a
